{
  "generator-jhipster": {
    "applicationType": "monolith",
    "gitCompany": "",
    "baseName": "ITAIMUI",
    "packageName": "com.itaimui.application",
    "packageFolder": "com/itaimui/application",
    "serverPort": 8081,
    "serviceDiscoveryType": false,
    "authenticationType": "jwt",
    "uaaBaseName": "../uaa",
    "cacheProvider": "ehcache",
    "enableHibernateCache": false,
    "websocket": false,
    "databaseType": "sql",
    "devDatabaseType": "mysql",
    "prodDatabaseType": "mysql",
    "searchEngine": "elasticsearch",
    "enableSwaggerCodegen": false,
    "messageBroker": false,
    "buildTool": "maven",
    "useSass": true,
    "clientPackageManager": "npm",
    "testFrameworks": [],
    "enableTranslation": true,
    "nativeLanguage": "en",
    "languages": [
      "en"
    ],
    "clientFramework": "angularX",
    "jhiPrefix": "jhi",
    "jhipsterVersion": "6.5.1",
    "jwtSecretKey": "OTlhNzdkNGQwMzZlZjJmZmFjY2I1YTBlODQxNGM2OWM2MzEwZmEzYTk1YTA4YzJmODViM2E4ZTQ4OTVmN2UxNmQzNWYyNjdmODZkMTZhNzc4NDc5OTk5MjI2NDRjNGZlMGIxODExOTY5ZmQ0OTI1N2I5Y2EzN2YyNDZhMDE4ZjM=",
    "embeddableLaunchScript": false,
    "clientTheme": "none",
    "entitySuffix": "",
    "dtoSuffix": "DTO",
    "otherModules": [],
    "blueprints": []
  },
  "git-provider": "GitHub",
  "git-company": "awarnasingh",
  "repository-name": "itaim-ui-app"
}